iniconfig.py
iniconfig-1.0.1.dist-info/LICENSE
iniconfig-1.0.1.dist-info/METADATA
iniconfig-1.0.1.dist-info/WHEEL
iniconfig-1.0.1.dist-info/top_level.txt
iniconfig-1.0.1.dist-info/RECORD
