Metadata-Version: 1.1
Name: iniconfig
Version: 1.0.1
Summary: iniconfig: brain-dead simple config-ini parsing
Home-page: http://github.com/RonnyPfannschmidt/iniconfig
Author: Ronny Pfannschmidt, Holger Krekel
Author-email: opensource@ronnypfannschmidt.de, holger.krekel@gmail.com
License: MIT License
Platform: unix
Platform: linux
Platform: osx
Platform: cygwin
Platform: win32
Classifier: Development Status :: 4 - Beta
Classifier: Intended Audience :: Developers
Classifier: License :: OSI Approved :: MIT License
Classifier: Operating System :: POSIX
Classifier: Operating System :: Microsoft :: Windows
Classifier: Operating System :: MacOS :: MacOS X
Classifier: Topic :: Software Development :: Libraries
Classifier: Topic :: Utilities
Classifier: Programming Language :: Python
Classifier: Programming Language :: Python :: 2
Classifier: Programming Language :: Python :: 3
